{
 "varer" : {
    "bukser" : {
      "bukse001" : {
        "merke1" : "ONLY & SONS",
        "merke2" : "",
        "type" : "Olabukse",
        "modell" : "Stretchy",
        "pris" : "429 kr",
        "anledning" : "fritid",
        "Farge1" : "blue",
        "Storrelse" : ["XS", "S", "M", "L", "XL"],
        "baerekraftig" : true,
        "Salg" : false,
        "Nyheter" : true,
        "kolleksjon" : "Vår",
        "bilde1" : "bilder_klær_riktig/bukse001a.jpg",
        "bilde2" : "bilder_klær_riktig/bukse001b.jpg",
        "bilde3" : "bilder_klær_riktig/bukse001c.jpg"

      },
      "bukse002" : {
        "merke1" : "Cayler",
        "merke2" : "",
        "type" : "Kortbukse",
        "modell" : "ripped",
        "pris" : "509 kr" ,
        "anledning" : "String",
        "Farge1" : ["grey","blue","red"],
        "Storrelse" : ["XS", "S", "M", "L", "XL"],
        "baerekraftig" : "Boolean",
        "Salg" : "Boolean",
        "Nyheter" : true,
        "kolleksjon" : "String",
        "bilde1" : "bilder_klær_riktig/bukse002a.jpg",
        "bilde2" : "bilder_klær_riktig/bukse002b.jpg",
        "bilde3" : "bilder_klær_riktig/bukse002c.jpg"

      },
      "bukse003" : {
        "merke1" : "Tommy Jeans",
        "merke2" : "",
        "type" : "Jobbebuksa",
        "modell" : "Tommy Joggebukse",
        "pris" : "580 kr",
        "anledning" : "Fritid",
        "Farge1" : ["grå","blå","rød"],
        "Storrelse" : ["XS", "S", "M", "L", "XL"],
        "baerekraftig" : false,
        "Salg" : false,
        "Nyheter" : true,
        "kolleksjon" : "høst",
        "bilde1" : "bilder_klær_riktig/bukse003a.jpg",
        "bilde2" : "bilder_klær_riktig/bukse003b.jpg",
        "bilde3" : "bilder_klær_riktig/bukse003c.jpg"

      },
      "bukse004" : {
        "merke1" : "Hugo Boss",
        "merke2" : "",
        "type" : "dress bukse",
        "modell" : "Slimfit dress pants",
        "pris" : "1800 kr" ,
        "anledning" : "formell",
        "Farge1" : ["grey","blue","black"],
        "Storrelse" : ["XS", "S", "M", "L", "XL"],
        "baerekraftig" : true,
        "Salg" : false,
        "Nyheter" : true,
        "kolleksjon" : "vinter",
        "bilde1" : "bilder_klær_riktig/bukse004a.jpg",
        "bilde2" : "bilder_klær_riktig/bukse004b.jpg",
        "bilde3" : "bilder_klær_riktig/bukse004c.jpg"

      },
      "bukse005" : {
        "merke1" : "adidas",
        "merke2" : "",
        "type" : "trening",
        "modell" : "adidas tracksuit pants",
        "pris" : " 580 kr",
        "anledning" : "Fritid",
        "Farge1" : ["grå","blå","rød"],
        "Storrelse" : ["XS", "S", "M", "L", "XL"],
        "baerekraftig" : false,
        "Salg" : false,
        "Nyheter" : true,
        "kolleksjon" : "høst",
        "bilde1" : "bilder_klær_riktig/bukse005a.jpg",
        "bilde2" : "bilder_klær_riktig/bukse005b.jpg",
        "bilde3" : "bilder_klær_riktig/bukse005c.jpg"

      },
      "bukse006" : {
        "merke1" : "adidas",
        "merke2" : "",
        "type" : "sport",
        "modell" : "adidas tracksuit pants",
        "pris" : "490 kr" ,
        "anledning" : "String",
        "Farge1" : ["grå","blå","rød"],
        "Storrelse" : ["XS", "S", "M", "L", "XL"],
        "baerekraftig" : false,
        "Salg" : false,
        "Nyheter" : false,
        "kolleksjon" : "høst",
        "bilde1" : "bilder_klær_riktig/bukse006a.jpg",
        "bilde2" : "bilder_klær_riktig/bukse006b.jpg",
        "bilde3" : "bilder_klær_riktig/bukse006c.jpg"
}
    },

    "skjorter" : {
      "skjorte001" : {
        "merke1" : "Ralph Lauren",
        "merke2" : "",
        "type" : "Rutete",
        "modell" : "OXFORD SLIM FIT",
        "pris" : "480 kr",
        "anledning" : "String",
        "Farge1" : ["grå","blå","rosa"],
        "Storrelse" : ["XS", "S", "M", "L", "XL"],
        "baerekraftig" : false,
        "Salg" : true,
        "Nyheter" : true,
        "kolleksjon" : "vår",
        "bilde1" : "bilder_klær_riktig/skjorte001a.jpg",
        "bilde2" : "bilder_klær_riktig/skjorte001b.jpg",
        "bilde3" : "bilder_klær_riktig/skjorte001c.jpg"


     },
      "skjorte002" : {
        "merke1" : "Tommy Hilfiger",
        "merke2" : "",
        "type" : "Stripete",
        "modell" : "SLIM FINE STRIPE SHIRT ",
        "pris" : "3800 kr" ,
        "anledning" : "formell",
        "Farge1" : ["grå","blå","hvit"],
        "Storrelse" : ["XS", "S", "M", "L", "XL"],
        "baerekraftig" : false,
        "Salg" : false,
        "Nyheter" : true,
        "kolleksjon" : "høst",
        "bilde1" : "bilder_klær_riktig/skjorte002a.jpg",
        "bilde2" : "bilder_klær_riktig/skjorte002b.jpg",
        "bilde3" : "bilder_klær_riktig/skjorte002c.jpg"

      },
      "skjorte003" : {
        "merke1" : "MANGO",
        "merke2" : "",
        "type" : "formell",
        "modell" : "AVISPA ",
        "pris" : "300 kr" ,
        "anledning" : "formell",
        "Farge1" : ["grå","blå","hvit"],
        "Storrelse" : ["XS", "S", "M", "L", "XL"],
        "baerekraftig" : true,
        "Salg" : false,
        "Nyheter" : true,
        "kolleksjon" : "høst",
        "bilde1" : "bilder_klær_riktig/skjorte003a.jpg",
        "bilde2" : "bilder_klær_riktig/skjorte003b.jpg",
        "bilde3" : "bilder_klær_riktig/skjorte003c.jpg"

      },"skjorte004" : {
        "merke1" : "TOPMAN",
        "merke2" : "",
        "type" : "Stripete",
        "modell" : "SLIM FINE STRIPE SHIRT ",
        "pris" : "3800 kr" ,
        "anledning" : "formell",
        "Farge1" : ["grå","blå","hvit"],
        "Storrelse" : ["XS", "S", "M", "L", "XL"],
        "baerekraftig" : false,
        "Salg" : false,
        "Nyheter" : true,
        "kolleksjon" : "høst",
        "bilde1" : "bilder_klær_riktig/skjorte004a.jpg",
        "bilde2" : "bilder_klær_riktig/skjorte042b.jpg",
        "bilde3" : "bilder_klær_riktig/skjorte004c.jpg"

      },"skjorte005" : {
        "merke1" : "PIER ONE",
        "merke2" : "JEAN PAUL",
        "type" : "casual",
        "modell" : "SLIM FINE STRIPE SHIRT ",
        "pris" : "3800 kr" ,
        "anledning" : "casual",
        "Farge1" : ["grå","blå","hvit"],
        "Storrelse" : ["XS", "S", "M", "L", "XL"],
        "baerekraftig" : false,
        "Salg" : false,
        "Nyheter" : true,
        "kolleksjon" : "høst",
        "bilde1" : "bilder_klær_riktig/skjorte005a.jpg",
        "bilde2" : "bilder_klær_riktig/skjorte005b.jpg",
        "bilde3" : "bilder_klær_riktig/skjorte005c.jpg"

      },"skjorte006" : {
        "merke1" : "LEVIS",
        "merke2" : "",
        "type" : "Stripete",
        "modell" : "SLIM FINE STRIPE SHIRT ",
        "pris" : "3800 kr" ,
        "anledning" : "formell",
        "Farge1" : ["grå","blå","hvit"],
        "Storrelse" : ["XS", "S", "M", "L", "XL"],
        "baerekraftig" : false,
        "Salg" : false,
        "Nyheter" : true,
        "kolleksjon" : "høst",
        "bilde1" : "bilder_klær_riktig/skjorte006a.jpg",
        "bilde2" : "bilder_klær_riktig/skjorte006b.jpg",
        "bilde3" : "bilder_klær_riktig/skjorte006c.jpg"

      }
    },
      "gensere" : {
        "genser001" : {
          "merke1" : "Raalph Lauren",
          "merke2" : "Bear",
          "type" : "",
          "modell" : "BLEND BEAR",
          "pris" : "380 kr" ,
          "anledning" : "formell",
          "Farge1" : ["grå","blå","rød"],
          "Storrelse" : ["XS", "S", "M", "L", "XL"],
          "baerekraftig" : false,
          "Salg" : false,
          "Nyheter" : false,
          "kolleksjon" : "høst",
          "bilde1" : "bilder_klær_riktig/genser001a.jpg",
          "bilde2" : "bilder_klær_riktig/genser001b.jpg",
          "bilde3" : "bilder_klær_riktig/genser001c.jpg"
        },

        "genser002" : {
          "merke1" : "Versace",
          "merke2" : "",
          "type" : "",
          "modell" : "HOODIE",
          "pris" : "380 kr" ,
          "anledning" : "casual",
          "Farge1" : ["grå","blå","rød"],
          "Storrelse" : ["XS", "S", "M", "L", "XL"],
          "baerekraftig" : false,
          "Salg" : false,
          "Nyheter" : false,
          "kolleksjon" : "sommer",
          "bilde1" : "bilder_klær_riktig/genser002a.jpg",
          "bilde2" : "bilder_klær_riktig/genser002b.jpg",
          "bilde3" : "bilder_klær_riktig/genser002c.jpg"
        },
        "genser003" : {
          "merke1" : "Holzweiler",
          "merke2" : "",
          "type" : "",
          "modell" : "HANGER HOODIE",
          "pris" : "1320 kr" ,
          "anledning" : "casual",
          "Farge1" : ["grå","blå","rød"],
          "Storrelse" : ["XS", "S", "M", "L", "XL"],
          "baerekraftig" : false,
          "Salg" : false,
          "Nyheter" : false,
          "kolleksjon" : "vinter",
          "bilde1" : "bilder_klær_riktig/genser003a.jpg",
          "bilde2" : "bilder_klær_riktig/genser003b.jpg",
          "bilde3" : "bilder_klær_riktig/genser003c.jpg"
        },
        "genser004" : {
          "merke1" : "BOSS",
          "merke2" : "HUGO Boss",
          "type" : "",
          "modell" : "THE BOSS",
          "pris" : "1450 kr" ,
          "anledning" : "casual",
          "Farge1" : ["grå","blå","rød"],
          "Storrelse" : ["XS", "S", "M", "L", "XL"],
          "baerekraftig" : false,
          "Salg" : false,
          "Nyheter" : false,
          "kolleksjon" : "høst",
          "bilde1" : "bilder_klær_riktig/genser004a.jpg",
          "bilde2" : "bilder_klær_riktig/genser004b.jpg",
          "bilde3" : "bilder_klær_riktig/genser004c.jpg"
        },
        "genser005" : {
          "merke1" : "MICHAEL KORS",
          "merke2" : "",
          "type" : "",
          "modell" : "LOGO HOODIE",
          "pris" : "1140 kr" ,
          "anledning" : "casual",
          "Farge1" : ["grå","blå","rød"],
          "Storrelse" : ["XS", "S", "M", "L", "XL"],
          "baerekraftig" : false,
          "Salg" : false,
          "Nyheter" : true,
          "kolleksjon" : "vår",
          "bilde1" : "bilder_klær_riktig/genser005a.jpg",
          "bilde2" : "bilder_klær_riktig/genser005b.jpg",
          "bilde3" : "bilder_klær_riktig/genser005c.jpg"
        },
        "genser006" : {
          "merke1" : "Gym king",
          "merke2" : "Bear",
          "type" : "",
          "modell" : "CREW",
          "pris" : "380 kr" ,
          "anledning" : "casual",
          "Farge1" : ["grå","blå","rød"],
          "Storrelse" : ["XS", "S", "M", "L", "XL"],
          "baerekraftig" : false,
          "Salg" : false,
          "Nyheter" : false,
          "kolleksjon" : "høst",
          "bilde1" : "bilder_klær_riktig/genser006a.jpg",
          "bilde2" : "bilder_klær_riktig/genser006b.jpg",
          "bilde3" : "bilder_klær_riktig/genser006c.jpg"
        }

    },


    "sport" : {
      "sport001" : {
        "merke1" : "adidas",
        "merke2" : "",
        "type" : "joggebukse",
        "modell" : "Stanford",
        "pris" : "180 kr" ,
        "anledning" : "trening",
        "Farge1" : ["grå","blå"],
        "Storrelse" : ["XS", "S", "M", "L", "XL"],
        "baerekraftig" : false,
        "Salg" : false,
        "Nyheter" : false,
        "kolleksjon" : "sommer",
        "bilde1" : "bilder_klær_riktig/sport001a.jpg",
        "bilde2" : "bilder_klær_riktig/sport001b.jpg",
        "bilde3" : "bilder_klær_riktig/sport001c.jpg"
      },
      "sport002" : {
        "merke1" : "nike",
        "merke2" : "",
        "type" : "tights",
        "modell" : "adapt run",
        "pris" : "180 kr",
        "anledning" : "trening",
        "Farge1" : ["grå","blå"],
        "Storrelse" : ["XS", "S", "M", "L", "XL"],
        "baerekraftig" : false,
        "Salg" : false,
        "Nyheter" : false,
        "kolleksjon" : "sommer",
        "bilde1" : "bilder_klær_riktig/sport002a.jpg",
        "bilde2" : "bilder_klær_riktig/sport002b.jpg",
        "bilde3" : "bilder_klær_riktig/sport002a.jpg"
      },
      "sport003" : {
        "merke1" : "nike",
        "merke2" : "",
        "type" : "overdel",
        "modell" : "DRY TEE",
        "pris" : "450 kr" ,
        "anledning" : "trening",
        "Farge1" : ["grå","blå"],
        "Storrelse" : ["XS", "S", "M", "L", "XL"],
        "baerekraftig" : false,
        "Salg" : false,
        "Nyheter" : true,
        "kolleksjon" : "vår",
        "bilde1" : "bilder_klær_riktig/sport003a.jpg",
        "bilde2" : "bilder_klær_riktig/sport003b.jpg",
        "bilde3" : "bilder_klær_riktig/sport003c.jpg"
      },
      "sport004" : {
        "merke1" : "nike",
        "merke2" : "",
        "type" : "overdel",
        "modell" : "crew neck",
        "pris" : "340 kr" ,
        "anledning" : "trening",
        "Farge1" : ["grå","blå"],
        "Storrelse" : ["XS", "S", "M", "L", "XL"],
        "baerekraftig" : false,
        "Salg" : true,
        "Nyheter" : false,
        "kolleksjon" : "sommer",
        "bilde1" : "bilder_klær_riktig/sport004a.jpg",
        "bilde2" : "bilder_klær_riktig/sport004b.jpg",
        "bilde3" : "bilder_klær_riktig/sport004c.jpg"
      },
      "sport005" : {
        "merke1" : "nike",
        "merke2" : "",
        "type" : "overdel",
        "modell" : "ZIP HOODIE",
        "pris" : "860 kr" ,
        "anledning" : "trening",
        "Farge1" : ["grå","blå"],
        "Storrelse" : ["XS", "S", "M", "L", "XL"],
        "baerekraftig" : false,
        "Salg" : false,
        "Nyheter" : false,
        "kolleksjon" : "sommer",
        "bilde1" : "bilder_klær_riktig/sport005a.jpg",
        "bilde2" : "bilder_klær_riktig/sport005b.jpg",
        "bilde3" : "bilder_klær_riktig/sport005c.jpg"
      },
      "sport006" : {
        "merke1" : "BOSS",
        "merke2" : "HUGO BOSS",
        "type" : "overdel",
        "modell" : "SICON",
        "pris" : "1600 kr" ,
        "anledning" : "trening",
        "Farge1" : ["grå","blå"],
        "Storrelse" : ["XS", "S", "M", "L", "XL"],
        "baerekraftig" : false,
        "Salg" : false,
        "Nyheter" : true,
        "kolleksjon" : "vår",
        "bilde1" : "bilder_klær_riktig/sport006a.jpg",
        "bilde2" : "bilder_klær_riktig/sport006b.jpg",
        "bilde3" : "bilder_klær_riktig/sport006c.jpg"
      }

    },
    "jakker" : {
      "jakke001" : {
        "merke1" : "Tommy hilfiger",
        "merke2" : "",
        "type" : "Stripete",
        "modell" : "Trck Jacket",
        "pris" : " 1195kr",
        "anledning" : "casual",
        "Farge1" : ["blå","svart"],
        "Storrelse" : ["XS", "S", "M", "L", "XL"],
        "baerekraftig" : false,
        "Salg" : false,
        "Nyheter" : true,
        "kolleksjon" : "vår",
        "bilde1" : "bilder_klær_riktig/jakke001a.jpg",
        "bilde2" : "bilder_klær_riktig/jakke001b.jpg",
        "bilde3" : "bilder_klær_riktig/jakke001c.jpg"
      },
      "jakke002" : {
        "merke1" : "versace",
        "merke2" : "",
        "type" : "print",
        "modell" : "Bombejakke",
        "pris" : " 2399kr",
        "anledning" : "casual",
        "Farge1" : ["blå","svart"],
        "Storrelse" : ["XS", "S", "M", "L", "XL"],
        "baerekraftig" : false,
        "Salg" : false,
        "Nyheter" : false,
        "kolleksjon" : "høst",
        "bilde1" : "bilder_klær_riktig/jakke002a.jpg",
        "bilde2" : "bilder_klær_riktig/jakke002b.jpg",
        "bilde3" : "bilder_klær_riktig/jakke002c.jpg"
      },
      "jakke003" : {
        "merke1" : "Gant",
        "merke2" : "",
        "type" : "plain",
        "modell" : "THE COMFORT",
        "pris" : " 1699kr",
        "anledning" : "casual",
        "Farge1" : ["blå","svart"],
        "Storrelse" : ["XS", "S", "M", "L", "XL"],
        "baerekraftig" : false,
        "Salg" : false,
        "Nyheter" : false,
        "kolleksjon" : "sommer",
        "bilde1" : "bilder_klær_riktig/jakke003a.jpg",
        "bilde2" : "bilder_klær_riktig/jakke003b.jpg",
        "bilde3" : "bilder_klær_riktig/jakke003c.jpg"
      },
      "jakke004" : {
        "merke1" : "napapijiri",
        "merke2" : "",
        "type" : "print",
        "modell" : "RAINFOREST",
        "pris" : " 899kr",
        "anledning" : "casual",
        "Farge1" : ["blå","svart"],
        "Storrelse" : ["XS", "S", "M", "L", "XL"],
        "baerekraftig" : false,
        "Salg" : false,
        "Nyheter" : true,
        "kolleksjon" : "vår",
        "bilde1" : "bilder_klær_riktig/jakke004a.jpg",
        "bilde2" : "bilder_klær_riktig/jakke004b.jpg",
        "bilde3" : "bilder_klær_riktig/jakke004c.jpg"
      },
      "jakke005" : {
        "merke1" : "HUGO",
        "merke2" : "",
        "type" : "plain",
        "modell" : "Innsvinget",
        "pris" : " 3999kr",
        "anledning" : "casual",
        "Farge1" : ["blå","svart"],
        "Storrelse" : ["XS", "S", "M", "L", "XL"],
        "baerekraftig" : false,
        "Salg" : false,
        "Nyheter" : true,
        "kolleksjon" : "vinter",
        "bilde1" : "bilder_klær_riktig/jakke005a.jpg",
        "bilde2" : "bilder_klær_riktig/jakke005b.jpg",
        "bilde3" : "bilder_klær_riktig/jakke005c.jpg"
      },
      "jakke006" : {
        "merke1" : "Morris",
        "merke2" : "",
        "type" : "plain",
        "modell" : "DRAYCOTT",
        "pris" : " 2599kr",
        "anledning" : "casual",
        "Farge1" : ["blå","svart"],
        "Storrelse" : ["XS", "S", "M", "L", "XL"],
        "baerekraftig" : false,
        "Salg" : false,
        "Nyheter" : true,
        "kolleksjon" : "vår",
        "bilde1" : "bilder_klær_riktig/jakke006a.jpg",
        "bilde2" : "bilder_klær_riktig/jakke006b.jpg",
        "bilde3" : "bilder_klær_riktig/jakke006c.jpg"
      }
    },
    "sko" : {
      "sko001" : {
        "merke1" : "Versace",
        "merke2" : "",
        "type" : "joggesko",
        "modell" : "Høye joggesko",
        "pris" : "3459 kr",
        "anledning" : "casual",
        "Farge1" : ["grå","blå","rød"],
        "Storrelse" : ["XS", "S", "M", "L", "XL"],
        "baerekraftig" : false,
        "Salg" : false,
        "Nyheter" : true,
        "kolleksjon" : "sommer",
        "bilde1" : "bilder_klær_riktig/sko001a.jpg",
        "bilde2" : "bilder_klær_riktig/sko001b.jpg",
        "bilde3" : "bilder_klær_riktig/sko001c.jpg"
      },
      "sko002" : {
        "merke1" : "BOSS",
        "merke2" : "",
        "type" : "formell",
        "modell" : "Kensignton",
        "pris" : "2759 kr",
        "anledning" : "formell",
        "Farge1" : ["grå","blå","rød"],
        "Storrelse" : ["XS", "S", "M", "L", "XL"],
        "baerekraftig" : false,
        "Salg" : false,
        "Nyheter" : true,
        "kolleksjon" : "sommer",
        "bilde1" : "bilder_klær_riktig/sko002a.jpg",
        "bilde2" : "bilder_klær_riktig/sko002b.jpg",
        "bilde3" : "bilder_klær_riktig/sko002c.jpg"
      },
      "sko003" : {
        "merke1" : "PUMA",
        "merke2" : "",
        "type" : "treningsko",
        "modell" : "ONE 19",
        "pris" : "759 kr",
        "anledning" : "fritid",
        "Farge1" : ["blå","rød"],
        "Storrelse" : ["XS", "S", "M", "L", "XL"],
        "baerekraftig" : false,
        "Salg" : false,
        "Nyheter" : true,
        "kolleksjon" : "sommer",
        "bilde1" : "bilder_klær_riktig/sko003a.jpg",
        "bilde2" : "bilder_klær_riktig/sko003b.jpg",
        "bilde3" : "bilder_klær_riktig/sko003c.jpg"
      },
      "sko004" : {
        "merke1" : "NIKE",
        "merke2" : "",
        "type" : "",
        "modell" : "",
        "pris" : "759 kr",
        "anledning" : "fritid",
        "Farge1" : ["grå","blå","rød"],
        "Storrelse" : ["XS", "S", "M", "L", "XL"],
        "baerekraftig" : false,
        "Salg" : false,
        "Nyheter" : true,
        "kolleksjon" : "sommer",
        "bilde1" : "bilder_klær_riktig/sko004a.jpg",
        "bilde2" : "bilder_klær_riktig/sko004b.jpg",
        "bilde3" : "bilder_klær_riktig/sko004c.jpg"
      },
      "sko005" : {
        "merke1" : "Melvin",
        "merke2" : "Hamilton",
        "type" : "pensko",
        "modell" : "Toni",
        "pris" : "759 kr",
        "anledning" : "formell",
        "Farge1" : ["brun"],
        "Storrelse" : ["XS", "S", "M", "L", "XL"],
        "baerekraftig" : false,
        "Salg" : false,
        "Nyheter" : true,
        "kolleksjon" : "sommer",
        "bilde1" : "bilder_klær_riktig/sko005a.jpg",
        "bilde2" : "bilder_klær_riktig/sko005b.jpg",
        "bilde3" : "bilder_klær_riktig/sko005c.jpg"
      },
      "sko006" : {
        "merke1" : "Versace",
        "merke2" : "",
        "type" : "pensko",
        "modell" : "Mokkasiner",
        "pris" : "4759 kr",
        "anledning" : "formell",
        "Farge1" : ["grå","blå","rød"],
        "Storrelse" : ["XS", "S", "M", "L", "XL"],
        "baerekraftig" : false,
        "Salg" : false,
        "Nyheter" : true,
        "kolleksjon" : "sommer",
        "bilde1" : "bilder_klær_riktig/sko006a.jpg",
        "bilde2" : "bilder_klær_riktig/sko006b.jpg",
        "bilde3" : "bilder_klær_riktig/sko006c.jpg"
      }

    },
    "tilbehor" : {
      "tilbehor001" : {
        "merke1" : "Versace",
        "merke2" : "",
        "type" : "klokke",
        "modell" : "PALAZZO",
        "pris" : "1469kr",
        "anledning" : "",
        "Farge1" : ["svart","blå"],
        "Storrelse" : ["XS", "S", "M", "L", "XL"],
        "baerekraftig" : false,
        "Salg" : false,
        "Nyheter" : true,
        "kolleksjon" : "høst",
        "bilde1" : "bilder_klær_riktig/tilbehor001a.jpg",
        "bilde2" : "bilder_klær_riktig/tilbehor001b.jpg",
        "bilde3" : "bilder_klær_riktig/tilbehor001c.jpg"
      },
      "tilbehor002" : {
        "merke1" : "FOSSIL",
        "merke2" : "",
        "type" : "bag",
        "modell" : "DEFENDER",
        "pris" : "4219kr",
        "anledning" : "",
        "Farge1" : ["svart"],
        "Storrelse" : ["XS", "S", "M", "L", "XL"],
        "baerekraftig" : false,
        "Salg" : true,
        "Nyheter" : true,
        "kolleksjon" : "vår",
        "bilde1" : "bilder_klær_riktig/tilbehor002a.jpg",
        "bilde2" : "bilder_klær_riktig/tilbehor002b.jpg",
        "bilde3" : "bilder_klær_riktig/tilbehor002c.jpg"
      },

      "tilbehor003" : {
        "merke1" : "VERSACE",
        "merke2" : "",
        "type" : "kjede",
        "modell" : "Necklace",
        "pris" : "4799kr",
        "anledning" : "",
        "Storrelse" : ["XS", "S", "M", "L", "XL"],
        "baerekraftig" : false,
        "Salg" : false,
        "Nyheter" : true,
        "kolleksjon" : "høst",
        "bilde1" : "bilder_klær_riktig/tilbehor003a.jpg",
        "bilde2" : "bilder_klær_riktig/tilbehor003b.jpg",
        "bilde3" : "bilder_klær_riktig/tilbehor003c.jpg"
      },
      "tilbehor004" : {
        "merke1" : "Dolce&Gabbana",
        "merke2" : "",
        "type" : "solbriller",
        "modell" : "Solbriller",
        "pris" : "4699kr",
        "anledning" : "",
        "Farge1" : ["svart","blå"],
        "Storrelse" : ["XS", "S", "M", "L", "XL"],
        "baerekraftig" : false,
        "Salg" : false,
        "Nyheter" : true,
        "kolleksjon" : "høst",
        "bilde1" : "bilder_klær_riktig/tilbehor004a.jpg",
        "bilde2" : "bilder_klær_riktig/tilbehor004b.jpg",
        "bilde3" : "bilder_klær_riktig/tilbehor004c.jpg"
      },
      "tilbehor005" : {
        "merke1" : "Columbia",
        "merke2" : "",
        "type" : "caps",
        "modell" : "Cap",
        "pris" : "259kr",
        "anledning" : "",
        "Farge1" : ["blå"],
        "Storrelse" : ["XS", "S", "M", "L", "XL"],
        "baerekraftig" : false,
        "Salg" : false,
        "Nyheter" : true,
        "kolleksjon" : "høst",
        "bilde1" : "bilder_klær_riktig/tilbehor005a.jpg",
        "bilde2" : "bilder_klær_riktig/tilbehor005b.jpg",
        "bilde3" : "bilder_klær_riktig/tilbehor005c.jpg"
      },
      "tilbehor006" : {
        "merke1" : "Tommy Hilfiger",
        "merke2" : "Mercedes Benz",
        "type" : "lommebok",
        "modell" : "Wallet",
        "pris" : "3469kr",
        "anledning" : "",
        "Farge1" : ["svart","blå"],
        "Storrelse" : ["XS", "S", "M", "L", "XL"],
        "baerekraftig" : false,
        "Salg" : false,
        "Nyheter" : true,
        "kolleksjon" : "høst",
        "bilde1" : "bilder_klær_riktig/tilbehor006a.jpg",
        "bilde2" : "bilder_klær_riktig/tilbehor006b.jpg",
        "bilde3" : "bilder_klær_riktig/tilbehor006c.jpg"
      }


    }



  }
}
